sentry_vsts/__init__.py
sentry_vsts/client.py
sentry_vsts/plugin.py
sentry_vsts-1.0.3.dist-info/DESCRIPTION.rst
sentry_vsts-1.0.3.dist-info/METADATA
sentry_vsts-1.0.3.dist-info/RECORD
sentry_vsts-1.0.3.dist-info/WHEEL
sentry_vsts-1.0.3.dist-info/entry_points.txt
sentry_vsts-1.0.3.dist-info/metadata.json
sentry_vsts-1.0.3.dist-info/top_level.txt
