Metadata-Version: 2.0
Name: sentry-vsts
Version: 1.0.3
Summary: A Sentry.io plugin for Visual Studio Team Services     integration
Home-page: https://github.com/boylec/sentry-vsts
Author: Casey Boyle
Author-email: boylec@live.com
License: MIT
Keywords: sentry-vsts sentry vsts visual studio team services sentry.io
Platform: UNKNOWN
Classifier: Framework :: Django
Classifier: Intended Audience :: Developers
Classifier: Intended Audience :: System Administrators
Classifier: Operating System :: OS Independent
Classifier: Topic :: Software Development
Requires-Dist: sentry (>=4.6.0)
Requires-Dist: requests (>=0.12.1)
